mutcli/__init__.py
mutcli/__main__.py
mutcli/cli.py
mutcli/core/__init__.py
mutcli/core/adb_state_monitor.py
mutcli/core/ai_analyzer.py
mutcli/core/analysis_io.py
mutcli/core/config.py
mutcli/core/device_controller.py
mutcli/core/executor.py
mutcli/core/frame_extractor.py
mutcli/core/parser.py
mutcli/core/preview_server.py
mutcli/core/recorder.py
mutcli/core/report.py
mutcli/core/scrcpy_service.py
mutcli/core/step_analyzer.py
mutcli/core/step_collapsing.py
mutcli/core/touch_monitor.py
mutcli/core/typing_detector.py
mutcli/core/ui_element_parser.py
mutcli/core/verification_suggester.py
mutcli/core/yaml_generator.py
mutcli/models/__init__.py
mutcli/models/test.py
mutcli/templates/approval.html
mutcli/templates/report.html
mutcli/utils/__init__.py
mutcli-0.3.0.dist-info/METADATA
mutcli-0.3.0.dist-info/WHEEL
mutcli-0.3.0.dist-info/entry_points.txt
mutcli-0.3.0.dist-info/RECORD
