Metadata-Version: 2.4
Name: mutcli
Version: 0.3.0
Summary: Mobile UI Testing CLI - Run YAML-based mobile tests anywhere
Project-URL: Homepage, https://github.com/vladkarpman/mut
Project-URL: Documentation, https://github.com/vladkarpman/mut#readme
Project-URL: Repository, https://github.com/vladkarpman/mut
Project-URL: Issues, https://github.com/vladkarpman/mut/issues
Author: Vladislav Karpman
License-Expression: MIT
Keywords: android,automation,mobile,scrcpy,testing,ui
Classifier: Development Status :: 3 - Alpha
Classifier: Environment :: Console
Classifier: Intended Audience :: Developers
Classifier: License :: OSI Approved :: MIT License
Classifier: Operating System :: OS Independent
Classifier: Programming Language :: Python :: 3
Classifier: Programming Language :: Python :: 3.11
Classifier: Programming Language :: Python :: 3.12
Classifier: Topic :: Software Development :: Testing
Requires-Python: >=3.11
Requires-Dist: adbutils>=2.0.0
Requires-Dist: av>=12.0.0
Requires-Dist: google-api-core>=2.0.0
Requires-Dist: google-genai>=1.0.0
Requires-Dist: mysc>=0.5.0
Requires-Dist: numpy>=1.24.0
Requires-Dist: pillow>=10.0.0
Requires-Dist: python-dotenv>=1.0.0
Requires-Dist: pyyaml>=6.0
Requires-Dist: rich>=13.0.0
Requires-Dist: typer>=0.12.0
Provides-Extra: dev
Requires-Dist: mypy>=1.8.0; extra == 'dev'
Requires-Dist: pytest-asyncio>=0.23.0; extra == 'dev'
Requires-Dist: pytest>=8.0.0; extra == 'dev'
Requires-Dist: ruff>=0.1.0; extra == 'dev'
